multi_column_distribution_sampler/__init__.py
multi_column_distribution_sampler/multi_column_distribution_sampler.py
multi_column_distribution_sampler-0.0.1.dist-info/METADATA
multi_column_distribution_sampler-0.0.1.dist-info/WHEEL
multi_column_distribution_sampler-0.0.1.dist-info/licenses/LICENSE.txt
multi_column_distribution_sampler-0.0.1.dist-info/RECORD
