Metadata-Version: 2.3
Name: multi_column_distribution_sampler
Version: 0.0.1
Summary: Distribution based sampling for multiple categorical columms
Project-URL: Homepage, https://github.com/a-abrhm/multi_column_distribution_sampler
Project-URL: Bug Tracker, https://github.com/a-abrhm/multi_column_distribution_sampler/issues
Author-email: Alan Abraham <alan.abraham.tm@gmail.com>
License: MIT License
License-File: LICENSE.txt
Keywords: dataframe,distribution,distribution sampler,multi column sampler,multiple,multiple column sampling,pandas,representative sampling,sampler,sampling
Classifier: License :: OSI Approved :: MIT License
Classifier: Operating System :: OS Independent
Classifier: Programming Language :: Python :: 3
Requires-Python: >=3.7
